```java
package demo.jvm0104;

public class HelloByteCode {
    /*
      public static void main(java.lang.String[]);
    Code:
       0: bipush        100
       2: istore_1
       3: sipush        200
       6: istore_2
       7: sipush        300
      10: istore_3     //  将100,200,300压入操作数栈顶,然后存入本地变量表中
      11: iload_1
      12: iload_2     // 将100,200压入操作数栈中
      13: iadd       // 进行求和运算
      14: iload_3    // 将200压入操作数栈
      15: imul       // 进行求乘积运算
      16: istore        4 //将结果写入本地变量表中4号槽位
      18: iload_1       // 将本地变量1号槽位数据入栈，
      19: bipush        100 // 将100压入操作数栈
      21: if_icmple     35  //比较前者是否大于后者，若大于则进行到35行，调用静态方法
      24: getstatic     #2                  // Field java/lang/System.out:Ljava/io/PrintStream;
      27: ldc           #3                  // String a>100 //将100入栈，然后调用PrintStream.println方法，下面分析类似
      29: invokevirtual #4                  // Method java/io/PrintStream.println:(Ljava/lang/String;)V
      32: goto          43                   //定义出口
      35: getstatic     #2                  // Field java/lang/System.out:Ljava/io/PrintStream;
      38: ldc           #5                  // String a<=100
      40: invokevirtual #4                  // Method java/io/PrintStream.println:(Ljava/lang/String;)V
      43: new           #6                  // class demo/jvm0104/HelloByteCode
      46: dup
      47: invokespecial #7                  // Method "<init>":()V
      50: astore        5
      52: return
}
Process finished with exit code 0
     */
    public static void main(String[] args) {
        int a=100;
        int b=200;
        int c=300;
        int d=(a+b)*c;
        if(a>100){
            System.out.println("a>100");
        }
        else {
            System.out.println("a<=100");
        }



        HelloByteCode obj =new HelloByteCode();
    }
}
```